[ {"fileName":"1.jpg","title":"photo1","desc":"pho"},
  {"fileName":"2.jpg","title":"photo2","desc":"pho"},
  {"fileName":"3.jpg","title":"photo3","desc":"pho"},
  {"fileName":"4.jpg","title":"photo4","desc":"pho"},
  {"fileName":"5.jpg","title":"photo5","desc":"pho"},
  {"fileName":"6.jpg","title":"photo6","desc":"pho"},
  {"fileName":"7.jpg","title":"photo7","desc":"pho"},
  {"fileName":"8.jpg","title":"photo8","desc":"pho"},
  {"fileName":"9.jpg","title":"photo9","desc":"pho"},
  {"fileName":"10.jpg","title":"photo10","desc":"pho"},
  {"fileName":"11.jpg","title":"photo11","desc":"pho"},
  {"fileName":"12.jpg","title":"photo12","desc":"pho"},
  {"fileName":"13.jpg","title":"photo13","desc":"pho"},
  {"fileName":"14.jpg","title":"photo14","desc":"pho"},
  {"fileName":"15.jpg","title":"photo15","desc":"pho"},
  {"fileName":"16.jpg","title":"photo16","desc":"pho"}
]
